{"header":"<h1>Module <code><span>Logging_constants.Content_type</span></code></h1>","type":"documentation","uses_katex":false,"breadcrumbs":[{"name":"Index","href":"../../../../../index.html","kind":"leaf-page"},{"name":"gillian","href":"../../../../index.html","kind":"page"},{"name":"Gillian","href":"../../../index.html","kind":"module"},{"name":"Logging","href":"../../index.html","kind":"module"},{"name":"Logging_constants","href":"../index.html","kind":"module"},{"name":"Content_type","href":"#","kind":"module"}],"toc":[],"source_anchor":null,"preamble":"<p>Allowed strings for the <code>type_</code> field of a report</p><p>Allowed strings for the <code>type_</code> field of a report</p>","content":"<div class=\"odoc-spec\"><div class=\"spec value anchored\" id=\"val-debug\"><a href=\"#val-debug\" class=\"anchor\"></a><code><span><span class=\"keyword\">val</span> debug : string</span></code></div></div><div class=\"odoc-spec\"><div class=\"spec value anchored\" id=\"val-phase\"><a href=\"#val-phase\" class=\"anchor\"></a><code><span><span class=\"keyword\">val</span> phase : string</span></code></div></div><div class=\"odoc-spec\"><div class=\"spec value anchored\" id=\"val-proc_init\"><a href=\"#val-proc_init\" class=\"anchor\"></a><code><span><span class=\"keyword\">val</span> proc_init : string</span></code></div></div><div class=\"odoc-spec\"><div class=\"spec value anchored\" id=\"val-cmd\"><a href=\"#val-cmd\" class=\"anchor\"></a><code><span><span class=\"keyword\">val</span> cmd : string</span></code></div></div><div class=\"odoc-spec\"><div class=\"spec value anchored\" id=\"val-cmd_result\"><a href=\"#val-cmd_result\" class=\"anchor\"></a><code><span><span class=\"keyword\">val</span> cmd_result : string</span></code></div></div><div class=\"odoc-spec\"><div class=\"spec value anchored\" id=\"val-cmd_step\"><a href=\"#val-cmd_step\" class=\"anchor\"></a><code><span><span class=\"keyword\">val</span> cmd_step : string</span></code></div></div><div class=\"odoc-spec\"><div class=\"spec value anchored\" id=\"val-match_\"><a href=\"#val-match_\" class=\"anchor\"></a><code><span><span class=\"keyword\">val</span> match_ : string</span></code></div></div><div class=\"odoc-spec\"><div class=\"spec value anchored\" id=\"val-match_case\"><a href=\"#val-match_case\" class=\"anchor\"></a><code><span><span class=\"keyword\">val</span> match_case : string</span></code></div></div><div class=\"odoc-spec\"><div class=\"spec value anchored\" id=\"val-match_result\"><a href=\"#val-match_result\" class=\"anchor\"></a><code><span><span class=\"keyword\">val</span> match_result : string</span></code></div></div><div class=\"odoc-spec\"><div class=\"spec value anchored\" id=\"val-assertion\"><a href=\"#val-assertion\" class=\"anchor\"></a><code><span><span class=\"keyword\">val</span> assertion : string</span></code></div></div><div class=\"odoc-spec\"><div class=\"spec value anchored\" id=\"val-match_recovery\"><a href=\"#val-match_recovery\" class=\"anchor\"></a><code><span><span class=\"keyword\">val</span> match_recovery : string</span></code></div></div><div class=\"odoc-spec\"><div class=\"spec value anchored\" id=\"val-annotated_action\"><a href=\"#val-annotated_action\" class=\"anchor\"></a><code><span><span class=\"keyword\">val</span> annotated_action : string</span></code></div></div><div class=\"odoc-spec\"><div class=\"spec value anchored\" id=\"val-set_freed_info\"><a href=\"#val-set_freed_info\" class=\"anchor\"></a><code><span><span class=\"keyword\">val</span> set_freed_info : string</span></code></div></div>"}